README.md
setup.py
execbox/__init__.py
st_execbox.egg-info/PKG-INFO
st_execbox.egg-info/SOURCES.txt
st_execbox.egg-info/dependency_links.txt
st_execbox.egg-info/requires.txt
st_execbox.egg-info/top_level.txt