Metadata-Version: 2.1
Name: st-execbox
Version: 1.0.0
Summary: An editable text box for executing Python code live
Home-page: https://github.com/tvst/st-execbox
Author: Thiago Teixeira
Author-email: me@thiagot.com
License: Apache 2
Platform: UNKNOWN
Classifier: Programming Language :: Python :: 3
Classifier: License :: OSI Approved :: Apache Software License
Classifier: Operating System :: OS Independent
Requires-Python: >=3.5
